lookpin_pyspark_lib/__init__.py
lookpin_pyspark_lib/category_utill.py
lookpin_pyspark_lib/dataframe_utill.py
lookpin_pyspark_lib/datetime_utill.py
lookpin_pyspark_lib/omnious_color_enum.py
lookpin_pyspark_lib/omnious_fit_enum.py
lookpin_pyspark_lib/omnious_look_enum.py
lookpin_pyspark_lib/omnious_texture_enum.py
lookpin_pyspark_lib/omnious_util.py
lookpin_pyspark_lib/postgres_config.py
lookpin_pyspark_lib/spark_config.py
lookpin_pyspark_pkg-0.0.9.dist-info/LICENSE.txt
lookpin_pyspark_pkg-0.0.9.dist-info/METADATA
lookpin_pyspark_pkg-0.0.9.dist-info/WHEEL
lookpin_pyspark_pkg-0.0.9.dist-info/top_level.txt
lookpin_pyspark_pkg-0.0.9.dist-info/RECORD
