Metadata-Version: 2.1
Name: lookpin-pyspark-pkg
Version: 0.0.9
Summary: lookpin pyspark lib
Home-page: https://github.com/lookpin/lookpin-pyspark-pkg
Author: lookpin
Author-email: dev@lookpin.co.kr
Project-URL: Bug Tracker, https://github.com/lookpin/lookpin-pyspark-pkg/issues
Classifier: Programming Language :: Python :: 3
Classifier: License :: OSI Approved :: MIT License
Classifier: Operating System :: OS Independent
Requires-Python: >=3.6
License-File: LICENSE.txt
